setup.py
location/__init__.py
location/location.py
location.egg-info/PKG-INFO
location.egg-info/SOURCES.txt
location.egg-info/dependency_links.txt
location.egg-info/top_level.txt