Metadata-Version: 1.0
Name: location
Version: 0.0.2
Summary: just a python
Home-page: UNKNOWN
Author: leo
Author-email: leo19920823@gmail.com
License: MIT License
Keywords: location
Platform: any
